{
    "blocks":[
              {
              "type":"wall",
              "height":20,
              "width":200,
              "pushVectorX":0,
              "pushVectorY":0,
              "positionX":0.25,
              "positionY":0.1,
              "pushTime":0,
              "rotation":0
              },
              {
              "type":"wall",
              "height":20,
              "width":200,
              "pushVectorX":0,
              "pushVectorY":0,
              "positionX":0.25,
              "positionY":0.4,
              "pushTime":0,
              "rotation":0
              },
              {
              "type":"standart",
              "height":90,
              "width":90,
              "pushVectorX":0,
              "pushVectorY":1,
              "positionX":0.35,
              "positionY":0.25,
              "pushTime":0,
              "rotation":0
              },
              {
              "type":"standart",
              "height":90,
              "width":90,
              "pushVectorX":0,
              "pushVectorY":1,
              "positionX":0.15,
              "positionY":0.25,
              "pushTime":0,
              "rotation":0
              },
              {
              "type":"swipeable",
              "height":150,
              "width":90,
              "pushVectorX":0,
              "pushVectorY":1,
              "positionX":0.75,
              "positionY":0.2,
              "pushTime":0,
              "rotation":0
              },
              {
              "type":"swipeable",
              "height":150,
              "width":90,
              "pushVectorX":0,
              "pushVectorY":-1,
              "positionX":0.9,
              "positionY":0.8,
              "pushTime":0,
              "rotation":0
              },
              {
              "type":"wall",
              "height":20,
              "width":250,
              "pushVectorX":0,
              "pushVectorY":0,
              "positionX":0.15,
              "positionY":0.85,
              "pushTime":0,
              "rotation":90
              },
              {
              "type":"wall",
              "height":20,
              "width":250,
              "pushVectorX":0,
              "pushVectorY":0,
              "positionX":0.45,
              "positionY":0.85,
              "pushTime":0,
              "rotation":270
              },
              {
              "type":"wall",
              "height":20,
              "width":250,
              "pushVectorX":0,
              "pushVectorY":0,
              "positionX":0.15,
              "positionY":0.6,
              "pushTime":0,
              "rotation":270
              },
              {
              "type":"wall",
              "height":40,
              "width":300,
              "pushVectorX":0,
              "pushVectorY":0,
              "positionX":0.8,
              "positionY":0.0,
              "pushTime":0,
              "rotation":0
              }
              ,
              {
              "type":"wall",
              "height":20,
              "width":300,
              "pushVectorX":0,
              "pushVectorY":0,
              "positionX":0.8,
              "positionY":0.95,
              "pushTime":0,
              "rotation":0
              }
              ],
    "timeout":20,
    "priority":13,
    "name":"Level 13"
}